examples/__init__.py
examples/sample_app.py
examples/server_sample.py
ibm_appconfiguration/__init__.py
ibm_appconfiguration/appconfiguration.py
ibm_appconfiguration/version.py
ibm_appconfiguration/configurations/__init__.py
ibm_appconfiguration/configurations/configuration_handler.py
ibm_appconfiguration/configurations/internal/__init__.py
ibm_appconfiguration/configurations/internal/common/__init__.py
ibm_appconfiguration/configurations/internal/common/config_constants.py
ibm_appconfiguration/configurations/internal/common/config_messages.py
ibm_appconfiguration/configurations/internal/utils/__init__.py
ibm_appconfiguration/configurations/internal/utils/api_manager.py
ibm_appconfiguration/configurations/internal/utils/compute_percentage.py
ibm_appconfiguration/configurations/internal/utils/connectivity.py
ibm_appconfiguration/configurations/internal/utils/file_manager.py
ibm_appconfiguration/configurations/internal/utils/logger.py
ibm_appconfiguration/configurations/internal/utils/metering.py
ibm_appconfiguration/configurations/internal/utils/parser.py
ibm_appconfiguration/configurations/internal/utils/socket.py
ibm_appconfiguration/configurations/internal/utils/url_builder.py
ibm_appconfiguration/configurations/internal/utils/validators.py
ibm_appconfiguration/configurations/models/__init__.py
ibm_appconfiguration/configurations/models/configuration_type.py
ibm_appconfiguration/configurations/models/feature.py
ibm_appconfiguration/configurations/models/property.py
ibm_appconfiguration/configurations/models/rule.py
ibm_appconfiguration/configurations/models/segment.py
ibm_appconfiguration/configurations/models/segment_rules.py
ibm_appconfiguration_python_sdk-0.4.1.dist-info/licenses/LICENSE
integration_tests/__init__.py
integration_tests/test_integration.py
unit_tests/__init__.py
unit_tests/test_appconfiguration.py
unit_tests/configurations/__init__.py
unit_tests/configurations/test_configuration_handler.py
unit_tests/configurations/models/__init__.py
unit_tests/configurations/models/test_feature.py
ibm_appconfiguration_python_sdk-0.4.1.dist-info/METADATA
ibm_appconfiguration_python_sdk-0.4.1.dist-info/WHEEL
ibm_appconfiguration_python_sdk-0.4.1.dist-info/top_level.txt
ibm_appconfiguration_python_sdk-0.4.1.dist-info/RECORD
