Metadata-Version: 2.4
Name: ibm-appconfiguration-python-sdk
Version: 0.4.1
Summary: IBM Cloud App Configuration Python SDK
Home-page: https://github.com/IBM/appconfiguration-python-sdk
Author: IBM
Author-email: mdevsrvs@in.ibm.com
License: Apache 2.0
Keywords: python,ibm_appconfiguration,ibm,ibm cloud,feature_flags
Classifier: Development Status :: 5 - Production/Stable
Classifier: License :: OSI Approved :: Apache Software License
Classifier: Intended Audience :: Developers
Classifier: Programming Language :: Python :: 3
Requires-Python: >=3.0
License-File: LICENSE
Requires-Dist: python-dateutil<3.0.0,>=2.8
Requires-Dist: requests<3.0,>=2.32.2
Requires-Dist: websocket-client<2.0.0,>=1.8.0
Requires-Dist: ibm-cloud-sdk-core<4.0.0,>=3.20.3
Requires-Dist: pyyaml>=5.4.1
Requires-Dist: schema>=0.7.5
Requires-Dist: mmh3==5.0.1
Dynamic: author
Dynamic: author-email
Dynamic: classifier
Dynamic: description
Dynamic: description-content-type
Dynamic: home-page
Dynamic: keywords
Dynamic: license
Dynamic: license-file
Dynamic: requires-dist
Dynamic: requires-python
Dynamic: summary
